collective.regenv-1.0.0-py3.11-nspkg.pth
collective/regenv/__init__.py
collective/regenv/configure.zcml
collective/regenv/monkey.py
collective/regenv/registry.py
collective/regenv/testing.py
collective/regenv/tests/__init__.py
collective/regenv/tests/sample.yaml
collective/regenv/tests/test_registry.py
collective.regenv-1.0.0.dist-info/LICENSE.GPL
collective.regenv-1.0.0.dist-info/LICENSE.rst
collective.regenv-1.0.0.dist-info/METADATA
collective.regenv-1.0.0.dist-info/WHEEL
collective.regenv-1.0.0.dist-info/entry_points.txt
collective.regenv-1.0.0.dist-info/namespace_packages.txt
collective.regenv-1.0.0.dist-info/top_level.txt
collective.regenv-1.0.0.dist-info/RECORD
