Metadata-Version: 2.1
Name: collective.regenv
Version: 1.0.0
Summary: An add-on for Plone
Home-page: https://github.com/collective/collective.regenv
Author: mamico
Author-email: mauro.amico@gmail.com
License: GPL version 2
Project-URL: PyPI, https://pypi.org/project/collective.regenv/
Project-URL: Source, https://github.com/collective/collective.regenv
Project-URL: Tracker, https://github.com/collective/collective.regenv/issues
Keywords: Python Plone CMS
Classifier: Environment :: Web Environment
Classifier: Framework :: Plone
Classifier: Framework :: Plone :: Addon
Classifier: Framework :: Plone :: 5.2
Classifier: Framework :: Plone :: 6.0
Classifier: Programming Language :: Python
Classifier: Programming Language :: Python :: 2.7
Classifier: Programming Language :: Python :: 3.7
Classifier: Programming Language :: Python :: 3.8
Classifier: Programming Language :: Python :: 3.9
Classifier: Programming Language :: Python :: 3.10
Classifier: Programming Language :: Python :: 3.11
Classifier: Operating System :: OS Independent
Classifier: License :: OSI Approved :: GNU General Public License v2 (GPLv2)
Requires-Python: >=2.7, !=3.0.*, !=3.1.*, !=3.2.*, !=3.3.*, !=3.4.*, !=3.5.*
License-File: LICENSE.GPL
License-File: LICENSE.rst
Requires-Dist: setuptools
Requires-Dist: plone.api
Requires-Dist: plone.registry
Requires-Dist: PyYAML
Provides-Extra: test
Requires-Dist: plone.app.testing ; extra == 'test'
